ckeditor5_django4/__init__.py
ckeditor5_django4/fields.py
ckeditor5_django4/forms.py
ckeditor5_django4/urls.py
ckeditor5_django4/views.py
ckeditor5_django4/widgets.py
ckeditor5_django4/static/django_ckeditor_5/app.js
ckeditor5_django4/static/django_ckeditor_5/exemple.js
ckeditor5_django4/static/django_ckeditor_5/dist/bundle.js
ckeditor5_django4/static/django_ckeditor_5/dist/bundle.js.map
ckeditor5_django4/static/django_ckeditor_5/dist/styles.css
ckeditor5_django4/static/django_ckeditor_5/dist/styles.css.map
ckeditor5_django4/static/django_ckeditor_5/src/ckeditor.js
ckeditor5_django4/static/django_ckeditor_5/src/override-django.css
ckeditor5_django4/static/django_ckeditor_5/src/custom_plugins/imageediting.js
ckeditor5_django4/static/django_ckeditor_5/src/custom_plugins/imagetitle.js
ckeditor5_django4/static/django_ckeditor_5/src/custom_plugins/imagewithtitle.js
ckeditor5_django4/static/django_ckeditor_5/src/custom_plugins/imagetitle/imagetitlecommand.js
ckeditor5_django4/static/django_ckeditor_5/src/custom_plugins/imagetitle/imagetitleediting.js
ckeditor5_django4/static/django_ckeditor_5/src/custom_plugins/imagetitle/imagetitleui.js
ckeditor5_django4/static/django_ckeditor_5/src/custom_plugins/imagetitle/ui/titleformview.js
ckeditor5_django4/static/django_ckeditor_5/src/custom_plugins/sign/sign.css
ckeditor5_django4/static/django_ckeditor_5/src/custom_plugins/sign/sign.js
ckeditor5_django4/static/django_ckeditor_5/src/custom_plugins/sign/signcommand.js
ckeditor5_django4/static/django_ckeditor_5/src/custom_plugins/sign/signediting.js
ckeditor5_django4/static/django_ckeditor_5/src/custom_plugins/sign/signui.js
ckeditor5_django4/static/django_ckeditor_5/src/custom_plugins/theme/title.svg
ckeditor5_django4/static/django_ckeditor_5/src/custom_plugins/theme/titleform.css
ckeditor5_django4/templates/django_ckeditor_5/widget.html
ckeditor5_django4_HouseofAtreides-0.0.2.dist-info/LICENSE
ckeditor5_django4_HouseofAtreides-0.0.2.dist-info/METADATA
ckeditor5_django4_HouseofAtreides-0.0.2.dist-info/WHEEL
ckeditor5_django4_HouseofAtreides-0.0.2.dist-info/top_level.txt
ckeditor5_django4_HouseofAtreides-0.0.2.dist-info/RECORD
